sadie/__init__.py
sadie/agents/__init__.py
sadie/agents/base.py
sadie/agents/exceptions.py
sadie/agents/mixins.py
sadie/agents/spatial.py
sadie/agents/walkers.py
sadie/models/__init__.py
sadie/models/base.py
sadie/models/exceptions.py
sadie/models/simple.py
sadie-0.2.0.dist-info/AUTHORS.rst
sadie-0.2.0.dist-info/LICENSE
sadie-0.2.0.dist-info/METADATA
sadie-0.2.0.dist-info/WHEEL
sadie-0.2.0.dist-info/top_level.txt
sadie-0.2.0.dist-info/RECORD
