Metadata-Version: 2.1
Name: sadie
Version: 0.2.0
Summary: Sadie is an agent-based modelling environment for stochastic agents in discrete time in Euclidean space.
Home-page: https://github.com/chrisvoncsefalvay/sadie
Author: Chris von Csefalvay
Author-email: chris@chrisvoncsefalvay.com
License: MIT license
Keywords: sadie
Platform: UNKNOWN
Classifier: Development Status :: 2 - Pre-Alpha
Classifier: Intended Audience :: Developers
Classifier: License :: OSI Approved :: MIT License
Classifier: Natural Language :: English
Classifier: Programming Language :: Python :: 3
Classifier: Programming Language :: Python :: 3.5
Classifier: Programming Language :: Python :: 3.6
Classifier: Programming Language :: Python :: 3.7
Classifier: Programming Language :: Python :: 3.8
Requires-Python: >=3.5
